{"expand":"names,schema","startAt":0,"maxResults":50,"total":1,"issues":[{"expand":"editmeta,renderedFields,transitions,changelog,operations","id":"26735","self":"https://bug.javlin.eu/rest/api/2/issue/26735","key":"CLO-3609","fields":{"summary":"Incorrect Locale parsing in date2num() function","issuetype":{"self":"https://bug.javlin.eu/rest/api/2/issuetype/1","id":"1","description":"A problem which impairs or prevents the functions of the product.","iconUrl":"https://bug.javlin.eu/images/icons/issuetypes/bug.png","name":"Bug","subtask":false}}}]}